ssb_altinn3_util/__init__.py
ssb_altinn3_util/py.typed
ssb_altinn3_util/clients/__init__.py
ssb_altinn3_util/clients/altinn/__init__.py
ssb_altinn3_util/clients/altinn/altinn_api_client.py
ssb_altinn3_util/clients/altinn/api/__init__.py
ssb_altinn3_util/clients/altinn/api/application.py
ssb_altinn3_util/clients/altinn/api/storage.py
ssb_altinn3_util/clients/auth/__init__.py
ssb_altinn3_util/clients/auth/altinn_auth_client.py
ssb_altinn3_util/clients/auth/altinn_auth_client_config.py
ssb_altinn3_util/clients/auth/helpers/__init__.py
ssb_altinn3_util/clients/auth/helpers/altinn_client.py
ssb_altinn3_util/clients/auth/helpers/guardian_client.py
ssb_altinn3_util/clients/auth/helpers/http_helper.py
ssb_altinn3_util/clients/auth/helpers/keycloak_client.py
ssb_altinn3_util/clients/auth/helpers/secret_manager_client.py
ssb_altinn3_util/clients/decorators/__init__.py
ssb_altinn3_util/clients/decorators/simple_exception_wrapper.py
ssb_altinn3_util/clients/decorators/token_refresh.py
ssb_altinn3_util/clients/gcp/__init__.py
ssb_altinn3_util/clients/gcp/publisher.py
ssb_altinn3_util/clients/gcp/subscriber_thread.py
ssb_altinn3_util/constants/__init__.py
ssb_altinn3_util/constants/enums.py
ssb_altinn3_util/models/__init__.py
ssb_altinn3_util/models/altinn3_cloud_event.py
ssb_altinn3_util/models/basic_file.py
ssb_altinn3_util/models/instantiation_request.py
ssb_altinn3_util/models/pagination.py
ssb_altinn3_util/models/skjemadata/skjemadata_request_models.py
ssb_altinn3_util/models/skjemadata/skjemadata_response_models.py
ssb_altinn3_util/observability/__init__.py
ssb_altinn3_util/observability/gcp_logger.py
ssb_altinn3_util/observability/gcp_tracer.py
ssb_altinn3_util/security/__init__.py
ssb_altinn3_util/security/auth_handler.py
ssb_altinn3_util/security/authenticator_constants.py
ssb_altinn3_util/security/authorization_request.py
ssb_altinn3_util/security/authorization_result.py
ssb_altinn3_util/security/authorization_userinfo.py
ssb_altinn3_util/security/form_access.py
ssb_altinn3_util-0.0.83.dist-info/METADATA
ssb_altinn3_util-0.0.83.dist-info/WHEEL
ssb_altinn3_util-0.0.83.dist-info/RECORD
