Metadata-Version: 2.4
Name: ssb_altinn3_util
Version: 0.0.83
Summary: A small library package containing various tools and utilities
Author-email: Anders Hagen <nhk@ssb.no>, Rannveig Aasen <rsa@ssb.no>, Lars-Roger Billingsø <lrb@ssb.no>, Sturla Josdal <lds@ssb.no>
Classifier: License :: OSI Approved :: MIT License
Classifier: Operating System :: OS Independent
Classifier: Programming Language :: Python :: 3
Requires-Python: >=3.9
Requires-Dist: cachetools
Requires-Dist: cryptography
Requires-Dist: defusedxml
Requires-Dist: fastapi
Requires-Dist: google-cloud-pubsub
Requires-Dist: google-cloud-secret-manager
Requires-Dist: opentelemetry-exporter-gcp-trace
Requires-Dist: opentelemetry-instrumentation
Requires-Dist: opentelemetry-instrumentation-logging
Requires-Dist: opentelemetry-propagator-gcp
Requires-Dist: pydantic
Requires-Dist: pyjwt
Requires-Dist: python-json-logger
